{
  "updated": "2026-04-11T16:48:53.517017+00:00",
  "count": 7,
  "rows": [
    {
      "sym": "JUP",
      "dex": "Orca",
      "bp": 0.1519,
      "dp": 0.1661,
      "diff": 0.0142,
      "pct": 9.3483,
      "liq": 58649.0
    },
    {
      "sym": "JTO",
      "dex": "Orca",
      "bp": 0.2838,
      "dp": 0.3066,
      "diff": 0.0228,
      "pct": 8.0338,
      "liq": 20464.0
    },
    {
      "sym": "ORCA",
      "dex": "Orca",
      "bp": 0.939,
      "dp": 0.9062,
      "diff": -0.0328,
      "pct": -3.4931,
      "liq": 717943.0
    },
    {
      "sym": "WIF",
      "dex": "Orca",
      "bp": 0.201,
      "dp": 0.1994,
      "diff": -0.0016,
      "pct": -0.796,
      "liq": 9436.0
    },
    {
      "sym": "RENDER",
      "dex": "Orca",
      "bp": 2.038,
      "dp": 2.05,
      "diff": 0.012,
      "pct": 0.5888,
      "liq": 32198.0
    },
    {
      "sym": "SOL",
      "dex": "Orca",
      "bp": 85.07,
      "dp": 85.092,
      "diff": 0.022,
      "pct": 0.0259,
      "liq": 27758727.0
    },
    {
      "sym": "BONK",
      "dex": "Raydium",
      "bp": 5.98e-06,
      "dp": 5.981e-06,
      "diff": 0.0,
      "pct": 0.0167,
      "liq": 176540.0
    }
  ]
}