{
  "updated": "2026-04-10T06:07:23.051514+00:00",
  "count": 6,
  "rows": [
    {
      "sym": "ORCA",
      "dex": "Orca",
      "bp": 0.834,
      "dp": 0.8996,
      "diff": 0.0656,
      "pct": 7.8657,
      "liq": 715234.0
    },
    {
      "sym": "JTO",
      "dex": "Orca",
      "bp": 0.2778,
      "dp": 0.2994,
      "diff": 0.0216,
      "pct": 7.7754,
      "liq": 20282.0
    },
    {
      "sym": "WIF",
      "dex": "Orca",
      "bp": 0.192,
      "dp": 0.2004,
      "diff": 0.0084,
      "pct": 4.375,
      "liq": 9458.0
    },
    {
      "sym": "RENDER",
      "dex": "Orca",
      "bp": 2.048,
      "dp": 2.052,
      "diff": 0.004,
      "pct": 0.1953,
      "liq": 32290.0
    },
    {
      "sym": "BONK",
      "dex": "Raydium",
      "bp": 5.94e-06,
      "dp": 5.946e-06,
      "diff": 1e-08,
      "pct": 0.101,
      "liq": 176038.0
    },
    {
      "sym": "SOL",
      "dex": "Orca",
      "bp": 83.43,
      "dp": 83.39,
      "diff": -0.04,
      "pct": -0.0479,
      "liq": 27069193.0
    }
  ]
}