{
  "updated": "2026-04-24T20:27:35.833743+00:00",
  "count": 6,
  "rows": [
    {
      "sym": "ORCA",
      "dex": "Orca",
      "bp": 0.979,
      "dp": 0.9366,
      "diff": -0.0424,
      "pct": -4.3309,
      "liq": 730569.0
    },
    {
      "sym": "JTO",
      "dex": "Orca",
      "bp": 0.3416,
      "dp": 0.3463,
      "diff": 0.0047,
      "pct": 1.3759,
      "liq": 21113.0
    },
    {
      "sym": "RENDER",
      "dex": "Orca",
      "bp": 1.788,
      "dp": 1.8,
      "diff": 0.012,
      "pct": 0.6711,
      "liq": 27417.0
    },
    {
      "sym": "WIF",
      "dex": "Orca",
      "bp": 0.179,
      "dp": 0.1797,
      "diff": 0.0007,
      "pct": 0.3911,
      "liq": 8988.0
    },
    {
      "sym": "BONK",
      "dex": "Raydium",
      "bp": 6.37e-06,
      "dp": 6.348e-06,
      "diff": -2e-08,
      "pct": -0.3454,
      "liq": 182635.0
    },
    {
      "sym": "SOL",
      "dex": "Orca",
      "bp": 86.27,
      "dp": 86.26,
      "diff": -0.01,
      "pct": -0.0116,
      "liq": 30368642.0
    }
  ]
}