{
  "updated": "2026-04-10T17:53:50.707324+00:00",
  "count": 7,
  "rows": [
    {
      "sym": "JTO",
      "dex": "Orca",
      "bp": 0.2778,
      "dp": 0.2996,
      "diff": 0.0218,
      "pct": 7.8474,
      "liq": 20290.0
    },
    {
      "sym": "JUP",
      "dex": "Orca",
      "bp": 0.1567,
      "dp": 0.1634,
      "diff": 0.0067,
      "pct": 4.2757,
      "liq": 57799.0
    },
    {
      "sym": "ORCA",
      "dex": "Orca",
      "bp": 0.939,
      "dp": 0.9063,
      "diff": -0.0327,
      "pct": -3.4824,
      "liq": 717941.0
    },
    {
      "sym": "WIF",
      "dex": "Orca",
      "bp": 0.192,
      "dp": 0.1968,
      "diff": 0.0048,
      "pct": 2.5,
      "liq": 9372.0
    },
    {
      "sym": "RENDER",
      "dex": "Orca",
      "bp": 2.043,
      "dp": 2.018,
      "diff": -0.025,
      "pct": -1.2237,
      "liq": 31824.0
    },
    {
      "sym": "SOL",
      "dex": "Orca",
      "bp": 84.76,
      "dp": 84.87,
      "diff": 0.11,
      "pct": 0.1298,
      "liq": 27557307.0
    },
    {
      "sym": "BONK",
      "dex": "Raydium",
      "bp": 5.92e-06,
      "dp": 5.926e-06,
      "diff": 1e-08,
      "pct": 0.1014,
      "liq": 175856.0
    }
  ]
}