{
  "updated": "2026-04-08T11:32:52.290108+00:00",
  "count": 6,
  "rows": [
    {
      "sym": "ORCA",
      "dex": "Orca",
      "bp": 0.834,
      "dp": 0.9008,
      "diff": 0.0668,
      "pct": 8.0096,
      "liq": 715622.0
    },
    {
      "sym": "JUP",
      "dex": "Orca",
      "bp": 0.1774,
      "dp": 0.1668,
      "diff": -0.0106,
      "pct": -5.9752,
      "liq": 58833.0
    },
    {
      "sym": "RENDER",
      "dex": "Orca",
      "bp": 2.09,
      "dp": 2.069,
      "diff": -0.021,
      "pct": -1.0048,
      "liq": 32588.0
    },
    {
      "sym": "WIF",
      "dex": "Orca",
      "bp": 0.198,
      "dp": 0.1991,
      "diff": 0.0011,
      "pct": 0.5556,
      "liq": 9423.0
    },
    {
      "sym": "BONK",
      "dex": "Raydium",
      "bp": 6.05e-06,
      "dp": 6.032e-06,
      "diff": -2e-08,
      "pct": -0.2975,
      "liq": 176870.0
    },
    {
      "sym": "SOL",
      "dex": "Orca",
      "bp": 84.59,
      "dp": 84.55,
      "diff": -0.04,
      "pct": -0.0473,
      "liq": 26698057.0
    }
  ]
}