{
  "updated": "2026-04-04T23:59:58.717045+00:00",
  "count": 6,
  "rows": [
    {
      "sym": "JTO",
      "dex": "Orca",
      "bp": 0.2619,
      "dp": 0.2787,
      "diff": 0.0168,
      "pct": 6.4147,
      "liq": 19763.0
    },
    {
      "sym": "ORCA",
      "dex": "Orca",
      "bp": 0.801,
      "dp": 0.8255,
      "diff": 0.0245,
      "pct": 3.0587,
      "liq": 684443.0
    },
    {
      "sym": "RENDER",
      "dex": "Orca",
      "bp": 1.894,
      "dp": 1.86,
      "diff": -0.034,
      "pct": -1.7951,
      "liq": 30078.0
    },
    {
      "sym": "WIF",
      "dex": "Orca",
      "bp": 0.183,
      "dp": 0.1811,
      "diff": -0.0019,
      "pct": -1.0383,
      "liq": 8967.0
    },
    {
      "sym": "BONK",
      "dex": "Raydium",
      "bp": 5.7e-06,
      "dp": 5.693e-06,
      "diff": -1e-08,
      "pct": -0.1228,
      "liq": 172495.0
    },
    {
      "sym": "SOL",
      "dex": "Orca",
      "bp": 80.78,
      "dp": 80.77,
      "diff": -0.01,
      "pct": -0.0124,
      "liq": 27853279.0
    }
  ]
}