{
  "updated": "2026-04-25T18:30:23.222708+00:00",
  "count": 5,
  "rows": [
    {
      "sym": "JUP",
      "dex": "Orca",
      "bp": 0.1678,
      "dp": 0.1709,
      "diff": 0.0031,
      "pct": 1.8474,
      "liq": 62019.0
    },
    {
      "sym": "WIF",
      "dex": "Orca",
      "bp": 0.178,
      "dp": 0.1766,
      "diff": -0.0014,
      "pct": -0.7865,
      "liq": 8910.0
    },
    {
      "sym": "BONK",
      "dex": "Raydium",
      "bp": 6.16e-06,
      "dp": 6.178e-06,
      "diff": 2e-08,
      "pct": 0.2922,
      "liq": 180936.0
    },
    {
      "sym": "RENDER",
      "dex": "Orca",
      "bp": 1.773,
      "dp": 1.77,
      "diff": -0.003,
      "pct": -0.1692,
      "liq": 26973.0
    },
    {
      "sym": "SOL",
      "dex": "Orca",
      "bp": 85.69,
      "dp": 85.73,
      "diff": 0.04,
      "pct": 0.0467,
      "liq": 30254730.0
    }
  ]
}